{"-1": {"http://lv2plug.in/ns/extensions/ui#X11UI": true, "http://lv2plug.in/ns/ext/options#supportedOption": "http://lv2plug.in/ns/extensions/ui#scaleFactor", "http://lv2plug.in/ns/extensions/ui#binary": "file:///home/djshaji/projects/ModularAmpToolKit.lv2-android/PreAmps/PreAmps_ui.so", "extensionData": "http://lv2plug.in/ns/extensions/ui#idleInterface", "optionalFeature": "http://lv2plug.in/ns/ext/options#options", "requiredFeature": "http://lv2plug.in/ns/extensions/ui#idleInterface", "pluginName": "PreAmps"}, "0": {"AudioPort": true, "InputPort": true, "index": 0, "name": "In0", "symbol": "in0"}, "1": {"AudioPort": true, "OutputPort": true, "index": 1, "name": "Out0", "symbol": "out0"}, "2": {"InputPort": true, "ControlPort": true, "default": 1, "designation": "http://lv2plug.in/ns/lv2core#enabled", "index": 2, "maximum": 1, "minimum": 0, "name": "bypass", "portProperty": "http://lv2plug.in/ns/lv2core#toggled", "symbol": "Bypass"}, "3": {"InputPort": true, "ControlPort": true, "default": "0.000000", "index": 3, "maximum": "20.000000", "minimum": "-20.000000", "name": "gain", "symbol": "GAIN"}, "4": {"InputPort": true, "ControlPort": true, "default": "0.000000", "index": 4, "maximum": "20.000000", "minimum": "-20.000000", "name": "volume", "symbol": "VOLUME"}, "5": {"InputPort": true, "ControlPort": true, "default": "0.0", "index": 5, "maximum": "3.0", "minimum": "0.0", "name": "ampselect", "portProperty": "http://lv2plug.in/ns/lv2core#enumeration", "scalePoint": "_:n84b2e68b474e43589039a19c917e86e6b10", "symbol": "AMPSELECT"}}